avatario_python_sdk/__init__.py
avatario_python_sdk/client.py
avatario_python_sdk-0.1.1.dist-info/licenses/LICENSE
avatario_python_sdk-0.1.1.dist-info/METADATA
avatario_python_sdk-0.1.1.dist-info/WHEEL
avatario_python_sdk-0.1.1.dist-info/top_level.txt
avatario_python_sdk-0.1.1.dist-info/RECORD
